bingen/__init__.py
bingen/models.py
bingen/translator.py
bingen/stardict/__init__.py
bingen/stardict/model.py
bingen/stardict/processor.py
bingen/stardict/de_dict/german_rus2.dict.dz
bingen/stardict/de_dict/german_rus2.idx
bingen/stardict/de_dict/german_rus2.ifo
bingen-0.1.4.dist-info/LICENSE
bingen-0.1.4.dist-info/METADATA
bingen-0.1.4.dist-info/WHEEL
bingen-0.1.4.dist-info/top_level.txt
bingen-0.1.4.dist-info/RECORD
