Metadata-Version: 2.1
Name: bingen
Version: 0.1.4
Summary: German to Ukrainian words translator
Home-page: https://github.com/adyachok/bingen
Author: Andras Gyacsok
Author-email: atti.dyachok@gmail.com
License: MIT
Platform: UNKNOWN
License-File: LICENSE
Requires-Dist: dataclasses-json
Requires-Dist: googletrans (==4.0.0rc1)
